EelForkExcludeFiles/__init__.py
EelForkExcludeFiles/__main__.py
EelForkExcludeFiles/browsers.py
EelForkExcludeFiles/chrome.py
EelForkExcludeFiles/edge.py
EelForkExcludeFiles/eel.js
EelForkExcludeFiles/electron.py
EelForkExcludeFiles-0.14.8.dist-info/LICENSE
EelForkExcludeFiles-0.14.8.dist-info/METADATA
EelForkExcludeFiles-0.14.8.dist-info/WHEEL
EelForkExcludeFiles-0.14.8.dist-info/top_level.txt
EelForkExcludeFiles-0.14.8.dist-info/RECORD
